audio_desilencer/__init__.py
audio_desilencer/audio_processor.py
AudioDeSilencer-1.1.dist-info/LICENSE
AudioDeSilencer-1.1.dist-info/METADATA
AudioDeSilencer-1.1.dist-info/WHEEL
AudioDeSilencer-1.1.dist-info/entry_points.txt
AudioDeSilencer-1.1.dist-info/top_level.txt
AudioDeSilencer-1.1.dist-info/RECORD
